CHANGES.txt
CONTRIBUTORS.txt
MANIFEST.in
README.txt
setup.cfg
setup.py
docs/HISTORY.txt
docs/INSTALL.txt
docs/LICENSE.GPL
docs/LICENSE.txt
docs/resources/tokenroleformconf.png
redomino/__init__.py
redomino/__init__.pyc
redomino.tokenroleform.egg-info/PKG-INFO
redomino.tokenroleform.egg-info/SOURCES.txt
redomino.tokenroleform.egg-info/dependency_links.txt
redomino.tokenroleform.egg-info/entry_points.txt
redomino.tokenroleform.egg-info/namespace_packages.txt
redomino.tokenroleform.egg-info/not-zip-safe
redomino.tokenroleform.egg-info/requires.txt
redomino.tokenroleform.egg-info/top_level.txt
redomino/tokenroleform/README.txt
redomino/tokenroleform/TODO.txt
redomino/tokenroleform/__init__.py
redomino/tokenroleform/config.py
redomino/tokenroleform/configure.zcml
redomino/tokenroleform/browser/__init__.py
redomino/tokenroleform/browser/configure.zcml
redomino/tokenroleform/content/__init__.py
redomino/tokenroleform/content/configure.zcml
redomino/tokenroleform/content/tokenrolemaileradapter.py
redomino/tokenroleform/interfaces/__init__.py
redomino/tokenroleform/interfaces/tokenrolemaileradapter.py
redomino/tokenroleform/portlets/__init__.py
redomino/tokenroleform/portlets/configure.zcml
redomino/tokenroleform/profiles/default/factorytool.xml
redomino/tokenroleform/profiles/default/metadata.xml
redomino/tokenroleform/profiles/default/portlets.xml
redomino/tokenroleform/profiles/default/propertiestool.xml
redomino/tokenroleform/profiles/default/rolemap.xml
redomino/tokenroleform/profiles/default/types.xml
redomino/tokenroleform/profiles/default/workflows.xml
redomino/tokenroleform/profiles/default/types/FormFolder.xml
redomino/tokenroleform/profiles/default/types/TokenRoleMailerAdapter.xml
redomino/tokenroleform/tests/__init__.py
redomino/tokenroleform/tests/base.py
redomino/tokenroleform/tests/test_doctest.py