Metadata-Version: 1.1
Name: redomino.tokenroleform
Version: 0.5
Summary: Token Role Form
Home-page: https://github.com/redomino/redomino.tokenroleform
Author: Davide Moro
Author-email: davide.moro@redomino.com
License: GPL
Platform: UNKNOWN
Classifier: Framework :: Plone
Classifier: Programming Language :: Python
Classifier: License :: OSI Approved :: GNU General Public License (GPL)
